cdk_ssm_document/__init__.py
cdk_ssm_document/py.typed
cdk_ssm_document/_jsii/__init__.py
cdk_ssm_document/_jsii/cdk-ssm-document@3.1.1.jsii.tgz
cdk_ssm_document-3.1.1.dist-info/LICENSE
cdk_ssm_document-3.1.1.dist-info/METADATA
cdk_ssm_document-3.1.1.dist-info/WHEEL
cdk_ssm_document-3.1.1.dist-info/top_level.txt
cdk_ssm_document-3.1.1.dist-info/RECORD
